MANIFEST.in
README.md
README.rst
setup.py
basicsudoku/__init__.py
basicsudoku/multisize.py
basicsudoku/puzzles.py
basicsudoku/solvers.py
basicsudoku.egg-info/PKG-INFO
basicsudoku.egg-info/SOURCES.txt
basicsudoku.egg-info/dependency_links.txt
basicsudoku.egg-info/top_level.txt
tests/multisize_test_basic.py
tests/test_basicsudoku.py