Metadata-Version: 1.1
Name: basicsudoku
Version: 0.1.1
Summary: A simple, basic Sudoku class in Python. Suitable for programming tutorials or experimentation.
Home-page: https://github.com/asweigart/basicsudoku
Author: Al Sweigart
Author-email: al@inventwithpython.com
License: BSD
Keywords: sudoku
Platform: UNKNOWN
Classifier: Development Status :: 4 - Beta
Classifier: License :: OSI Approved :: BSD License
Classifier: Operating System :: OS Independent
Classifier: Programming Language :: Python
Classifier: Programming Language :: Python :: 2
Classifier: Programming Language :: Python :: 2.6
Classifier: Programming Language :: Python :: 2.7
Classifier: Programming Language :: Python :: 3
Classifier: Programming Language :: Python :: 3.1
Classifier: Programming Language :: Python :: 3.2
Classifier: Programming Language :: Python :: 3.3
Classifier: Programming Language :: Python :: 3.4
Classifier: Programming Language :: Python :: 3.5
Classifier: Programming Language :: Python :: 3.6
Classifier: Programming Language :: Python :: 3.7
